processplatform/__init__.py
processplatform-1.0.4.dist-info/METADATA
processplatform-1.0.4.dist-info/WHEEL
processplatform-1.0.4.dist-info/top_level.txt
processplatform-1.0.4.dist-info/RECORD
