Metadata-Version: 2.1
Name: processplatform
Version: 1.0.4
Summary: Gain computer process information
Home-page: https://google.com
Author: vesper
Author-email: google@gmail.com
License: MIT
Keywords: process
Platform: UNKNOWN
Classifier: Development Status :: 5 - Production/Stable
Classifier: Intended Audience :: Education
Classifier: Operating System :: Microsoft :: Windows :: Windows 10
Classifier: License :: OSI Approved :: MIT License
Classifier: Programming Language :: Python :: 3
